kkpy/__init__.py
kkpy/cm.py
kkpy/io.py
kkpy/plot.py
kkpy/util.py
kkpy/SHP/gadm36_KOR_0.cpg
kkpy/SHP/gadm36_KOR_0.dbf
kkpy/SHP/gadm36_KOR_0.prj
kkpy/SHP/gadm36_KOR_0.shp
kkpy/SHP/gadm36_KOR_0.shx
kkpy/SHP/gadm36_KOR_1.cpg
kkpy/SHP/gadm36_KOR_1.dbf
kkpy/SHP/gadm36_KOR_1.prj
kkpy/SHP/gadm36_KOR_1.shp
kkpy/SHP/gadm36_KOR_1.shx
kkpy/SHP/gadm36_KOR_2.cpg
kkpy/SHP/gadm36_KOR_2.dbf
kkpy/SHP/gadm36_KOR_2.prj
kkpy/SHP/gadm36_KOR_2.shp
kkpy/SHP/gadm36_KOR_2.shx
kkpy-0.7.2.dist-info/LICENSE
kkpy-0.7.2.dist-info/METADATA
kkpy-0.7.2.dist-info/WHEEL
kkpy-0.7.2.dist-info/top_level.txt
kkpy-0.7.2.dist-info/RECORD
