Metadata-Version: 2.1
Name: kkpy
Version: 0.7.2
Summary: Python library for my meteorological research
Home-page: https://github.com/Kwonil-Kim/kkpy
Author: Kwonil Kim
Author-email: kwonil.kim.0@gmail.com
License: MIT
License-File: LICENSE
Requires-Dist: numpy
Requires-Dist: Cartopy
Requires-Dist: arm-pyart
Requires-Dist: matplotlib
Requires-Dist: haversine
Requires-Dist: scipy
Requires-Dist: dask
Requires-Dist: pandas
Requires-Dist: netCDF4
Requires-Dist: geopandas
Requires-Dist: descartes
Requires-Dist: xarray
Requires-Dist: bottleneck
Requires-Dist: scikit-image
Requires-Dist: astropy
Requires-Dist: parse
Requires-Dist: numba
